{
  "Ability1": "crystal_maiden_crystal_nova",
  "Ability10": "special_bonus_hp_200",
  "Ability11": "special_bonus_intelligence_12",
  "Ability12": "special_bonus_unique_crystal_maiden_frostbite_castrange",
  "Ability13": "special_bonus_unique_crystal_maiden_5",
  "Ability14": "special_bonus_attack_speed_225",
  "Ability15": "special_bonus_unique_crystal_maiden_3",
  "Ability16": "special_bonus_unique_crystal_maiden_1",
  "Ability17": "special_bonus_unique_crystal_maiden_2",
  "Ability2": "crystal_maiden_frostbite",
  "Ability3": "crystal_maiden_brilliance_aura",
  "Ability4": "crystal_maiden_crystal_clone",
  "Ability5": "crystal_maiden_blueheart_floe",
  "Ability6": "crystal_maiden_freezing_field",
  "Ability7": "crystal_maiden_freezing_field_stop",
  "AbilityDraftAbilities": {
    "Ability1": "crystal_maiden_crystal_nova",
    "Ability2": "crystal_maiden_frostbite",
    "Ability3": "crystal_maiden_brilliance_aura",
    "Ability4": "crystal_maiden_freezing_field"
  },
  "Adjectives": {
    "Blue": "1",
    "Cape": "1",
    "Cute": "1",
    "Female": "1",
    "Icy": "1"
  },
  "ArmorPhysical": "0",
  "AttackAcquisitionRange": "800",
  "AttackAnimationPoint": "0.450000",
  "AttackCapabilities": "DOTA_UNIT_CAP_RANGED_ATTACK",
  "AttackDamageMax": "34",
  "AttackDamageMin": "28",
  "AttackRange": "600",
  "AttackRate": "1.700000",
  "AttackSpeedActivityModifiers": {
    "fast": "200"
  },
  "AttributeAgilityGain": "1.800000",
  "AttributeBaseAgility": "16",
  "AttributeBaseIntelligence": "20",
  "AttributeBaseStrength": "17",
  "AttributeIntelligenceGain": "3.300000",
  "AttributePrimary": "DOTA_ATTRIBUTE_INTELLECT",
  "AttributeStrengthGain": "2.200000",
  "BanSound": "crystalmaiden_cm_anger_08",
  "BaseAttackSpeed": "100",
  "Bot": {
    "AggressionFactor": "0.800000",
    "Build": {
      "1": "crystal_maiden_frostbite",
      "2": "crystal_maiden_brilliance_aura",
      "3": "crystal_maiden_frostbite",
      "4": "crystal_maiden_brilliance_aura",
      "5": "crystal_maiden_frostbite",
      "6": "crystal_maiden_freezing_field",
      "7": "crystal_maiden_frostbite",
      "8": "crystal_maiden_brilliance_aura",
      "9": "crystal_maiden_brilliance_aura",
      "10": "special_bonus_intelligence_12",
      "11": "crystal_maiden_crystal_nova",
      "12": "crystal_maiden_freezing_field",
      "13": "crystal_maiden_crystal_nova",
      "14": "crystal_maiden_crystal_nova",
      "15": "special_bonus_unique_crystal_maiden_frostbite_castrange",
      "16": "crystal_maiden_crystal_nova",
      "17": "",
      "18": "crystal_maiden_freezing_field",
      "19": "",
      "20": "special_bonus_unique_crystal_maiden_3",
      "21": "",
      "22": "",
      "23": "",
      "24": "",
      "25": "special_bonus_unique_crystal_maiden_1"
    },
    "HeroType": "DOTA_BOT_PURE_SUPPORT",
    "LaningInfo": {
      "ProvidesBabysit": "2",
      "ProvidesSetup": "1",
      "RequiresBabysit": "0",
      "RequiresFarm": "1",
      "RequiresSetup": "0",
      "SoloDesire": "0",
      "SurvivalRating": "1"
    },
    "Loadout": {
      "item_black_king_bar": "ITEM_DERIVED",
      "item_blade_of_alacrity": "ITEM_EXTENSION",
      "item_blades_of_attack": "ITEM_EXTENSION",
      "item_boots": "ITEM_CORE",
      "item_chainmail": "ITEM_EXTENSION",
      "item_clarity": [
        "ITEM_CONSUMABLE | ITEM_SELLABLE",
        "ITEM_CONSUMABLE | ITEM_SELLABLE"
      ],
      "item_flask": "ITEM_CONSUMABLE | ITEM_SELLABLE",
      "item_magic_stick": "ITEM_CORE | ITEM_SELLABLE",
      "item_mithril_hammer": "ITEM_LUXURY",
      "item_ogre_axe": [
        "ITEM_EXTENSION",
        "ITEM_LUXURY"
      ],
      "item_phase_boots": "ITEM_DERIVED",
      "item_point_booster": "ITEM_EXTENSION",
      "item_recipe_black_king_bar": "ITEM_LUXURY",
      "item_staff_of_wizardry": "ITEM_EXTENSION",
      "item_tango": "ITEM_CONSUMABLE | ITEM_SELLABLE",
      "item_ultimate_scepter": "ITEM_DERIVED"
    }
  },
  "BotImplemented": "1",
  "BoundsHullName": "DOTA_HULL_SIZE_HERO",
  "CMEnabled": "1",
  "Complexity": "1",
  "Enabled": "1",
  "Facets": {
    "crystal_maiden_arcane_overflow": {
      "Color": "Blue",
      "GradientID": "2",
      "Icon": "mana"
    },
    "crystal_maiden_cold_comfort": {
      "Color": "Blue",
      "Deprecated": "true",
      "GradientID": "2",
      "Icon": "mana"
    },
    "crystal_maiden_frozen_expanse": {
      "Color": "Gray",
      "Deprecated": "true",
      "GradientID": "1",
      "Icon": "area_of_effect"
    },
    "crystal_maiden_glacial_guard": {
      "Color": "Gray",
      "GradientID": "3",
      "Icon": "armor"
    }
  },
  "GameSoundsFile": "soundevents/game_sounds_heroes/game_sounds_crystalmaiden.vsndevts",
  "GibType": "ice",
  "HasAggressiveStance": "1",
  "HeroGlowColor": "82 236 255",
  "HeroID": "5",
  "HeroOrderID": "3",
  "HeroPool1": "1",
  "HeroPool2": "1",
  "HeroSelectSoundEffect": "Hero_CrystalMaiden.Pick",
  "HeroUnlockOrder": "0",
  "IdleExpression": "scenes/crystalmaiden/crystalmaiden_exp_idle_05.vcd",
  "ItemSlots": {
    "0": {
      "MaxPolygonsLOD0": "2500",
      "MaxPolygonsLOD1": "1000",
      "SlotIndex": "0",
      "SlotName": "weapon",
      "SlotText": "#LoadoutSlot_Weapon",
      "TextureHeight": "256",
      "TextureWidth": "256"
    },
    "1": {
      "MaxPolygonsLOD0": "4000",
      "MaxPolygonsLOD1": "1600",
      "SlotIndex": "1",
      "SlotName": "back",
      "SlotText": "#LoadoutSlot_Back",
      "TextureHeight": "512",
      "TextureWidth": "512"
    },
    "2": {
      "MaxPolygonsLOD0": "1500",
      "MaxPolygonsLOD1": "600",
      "SlotIndex": "2",
      "SlotName": "arms",
      "SlotText": "#LoadoutSlot_Arms",
      "TextureHeight": "256",
      "TextureWidth": "256"
    },
    "3": {
      "MaxPolygonsLOD0": "3000",
      "MaxPolygonsLOD1": "1200",
      "SlotIndex": "3",
      "SlotName": "shoulder",
      "SlotText": "#LoadoutSlot_Shoulder",
      "TextureHeight": "512",
      "TextureWidth": "512"
    },
    "4": {
      "MaxPolygonsLOD0": "3000",
      "MaxPolygonsLOD1": "1200",
      "SlotIndex": "4",
      "SlotName": "head",
      "SlotText": "#LoadoutSlot_Head_Accessory",
      "TextureHeight": "512",
      "TextureWidth": "512"
    },
    "5": {
      "SlotIndex": "5",
      "SlotName": "taunt",
      "SlotText": "#LoadoutSlot_Taunt"
    },
    "6": {
      "DisplayInLoadout": "0",
      "SlotIndex": "6",
      "SlotName": "ambient_effects",
      "SlotText": "#LoadoutSlot_Ambient_Effects"
    },
    "7": {
      "DisplayInLoadout": "0",
      "SlotIndex": "7",
      "SlotName": "ability_effects_1",
      "SlotText": "crystal_maiden_crystal_nova"
    },
    "8": {
      "DisplayInLoadout": "0",
      "SlotIndex": "8",
      "SlotName": "ability_effects_2",
      "SlotText": "crystal_maiden_frostbite"
    },
    "9": {
      "DisplayInLoadout": "0",
      "SlotIndex": "9",
      "SlotName": "ability_effects_3",
      "SlotText": "crystal_maiden_brilliance_aura"
    },
    "10": {
      "DisplayInLoadout": "0",
      "SlotIndex": "10",
      "SlotName": "ability_effects_4",
      "SlotText": "crystal_maiden_freezing_field"
    },
    "11": {
      "MaxPolygonsLOD0": "4000",
      "MaxPolygonsLOD1": "2000",
      "SlotIndex": "11",
      "SlotName": "head_persona_1",
      "SlotText": "#LoadoutSlot_Head_Crystal_Maiden_Persona",
      "TextureHeight": "512",
      "TextureWidth": "512"
    },
    "12": {
      "MaxPolygonsLOD0": "4000",
      "MaxPolygonsLOD1": "2000",
      "SlotIndex": "12",
      "SlotName": "tail_persona_1",
      "SlotText": "#LoadoutSlot_Tail_Crystal_Maiden_Persona",
      "TextureHeight": "512",
      "TextureWidth": "512"
    },
    "13": {
      "MaxPolygonsLOD0": "3000",
      "MaxPolygonsLOD1": "1500",
      "SlotIndex": "13",
      "SlotName": "armor_persona_1",
      "SlotText": "#LoadoutSlot_Armor_Crystal_Maiden_Persona",
      "TextureHeight": "512",
      "TextureWidth": "512"
    },
    "14": {
      "MaxPolygonsLOD0": "1000",
      "MaxPolygonsLOD1": "500",
      "SlotIndex": "14",
      "SlotName": "misc_persona_1",
      "SlotText": "#LoadoutSlot_Misc_Crystal_Maiden_Persona",
      "TextureHeight": "256",
      "TextureWidth": "256"
    },
    "15": {
      "DisplayInLoadout": "1",
      "SlotIndex": "15",
      "SlotName": "taunt_persona_1",
      "SlotText": "#LoadoutSlot_Taunt_Crystal_Maiden_Persona"
    },
    "16": {
      "DisplayInLoadout": "0",
      "SlotIndex": "16",
      "SlotName": "ambient_effects_persona_1",
      "SlotText": "#LoadoutSlot_Ambient_Effects"
    },
    "17": {
      "GeneratesUnits": {
        "0": "npc_dota_companion"
      },
      "ShowItemOnGeneratedUnits": "1",
      "SlotIndex": "17",
      "SlotName": "summon_persona_1",
      "SlotText": "#LoadoutSlot_Pet_Crystal_Maiden_Persona"
    },
    "18": {
      "SlotIndex": "18",
      "SlotName": "persona_selector",
      "SlotText": "#LoadoutSlot_Persona_Selector"
    },
    "19": {
      "SlotIndex": "19",
      "SlotName": "hero_effigy",
      "SlotText": "#LoadoutSlot_HeroEffigy"
    },
    "20": {
      "SlotIndex": "20",
      "SlotName": "hero_effigy_persona_1",
      "SlotText": "#LoadoutSlot_HeroEffigy"
    }
  },
  "LastHitChallengeRival": "npc_dota_hero_lina",
  "LoadoutScale": "0.81",
  "Model": "models/heroes/crystal_maiden/crystal_maiden.vmdl",
  "ModelScale": "0.810000",
  "MovementSpeed": "280",
  "MovementSpeedActivityModifiers": {
    "run": "320",
    "run_fast": "345",
    "walk": "0"
  },
  "NameAliases": "cm;rylai;wolf",
  "Persona": {
    "1": {
      "Model": "models/heroes/crystal_maiden_persona/crystal_maiden_persona.vmdl",
      "mvp_map_override": "maps/scenes/mvp/mvp_crystal_maiden_persona.vmap",
      "name": "npc_dota_hero_crystal_maiden_persona1",
      "token": "#npc_dota_hero_crystal_maiden_persona1",
      "token_english": "#npc_dota_hero_crystal_maiden_persona1__en"
    }
  },
  "PickSound": "crystalmaiden_cm_spawn_01",
  "ProjectileModel": "particles/units/heroes/hero_crystalmaiden/maiden_base_attack.vpcf",
  "ProjectileSpeed": "900",
  "RenderablePortrait": {
    "Particles": {
      "particles/units/heroes/hero_crystalmaiden/maiden_loadout.vpcf": "loadout"
    }
  },
  "Role": "Support,Disabler,Nuker",
  "Rolelevels": "3,2,2",
  "SimilarHeroes": "87,3,31",
  "SoundSet": "hero_Crystal",
  "StatusManaRegen": "0",
  "Team": "Good",
  "VersusScale": "0.81",
  "VoiceFile": "soundevents/voscripts/game_sounds_vo_crystalmaiden.vsndevts",
  "animation_transitions": {
    "ACT_DOTA_IDLE": {
      "aggressive": "0.8",
      "regular": "0.80000"
    },
    "ACT_DOTA_RUN": {
      "aggressive": "0.6",
      "regular": "0.600000"
    }
  },
  "new_player_enable": "1",
  "particle_folder": "particles/units/heroes/hero_crystalmaiden",
  "party_hat_effects": {
    "party_hat_effect_0": "particles/econ/events/frostivus_2024/frostivus_2024_hat_ambient_npc_dota_hero_crystal_maiden.vpcf",
    "party_hat_effect_persona_0": "particles/econ/events/frostivus_2024/frostivus_2024_hat_ambient_npc_dota_hero_crystal_maiden_persona_1.vpcf"
  },
  "precache": {
    "particle": [
      "particles/econ/events/frostivus_2024/frostivus_2024_hat_ambient_npc_dota_hero_crystal_maiden.vpcf",
      "particles/econ/events/frostivus_2024/frostivus_2024_hat_ambient_npc_dota_hero_crystal_maiden_persona_1.vpcf"
    ]
  },
  "showcase_attachments": {
    "attach_attack2": "4",
    "attach_lookat": "5",
    "attach_mouth": "1",
    "attach_staff_base": "2",
    "attach_staff_tip": "3"
  },
  "workshop_guide_name": "Crystal Maiden"
}
