{
  "AbilityBehavior": "DOTA_ABILITY_BEHAVIOR_NO_TARGET | DOTA_ABILITY_BEHAVIOR_IMMEDIATE",
  "AbilityCastAnimation": "ACT_DOTA_CAST_ABILITY_4",
  "AbilityCastPoint": "0 0 0",
  "AbilityCooldown": "130 120 110",
  "AbilityDraftExtraAbilities": {
    "visage_silent_as_the_grave": "scepter",
    "visage_stone_form_self_cast": ""
  },
  "AbilityManaCost": "150 150 150",
  "AbilitySound": "Hero_Visage.SummonFamiliars.Cast",
  "AbilityType": "ABILITY_TYPE_ULTIMATE",
  "AbilityUnitDamageType": "DAMAGE_TYPE_PHYSICAL",
  "AbilityValues": {
    "additional_target_search_radius": {
      "affected_by_aoe_increase": "1",
      "value": "300"
    },
    "armor_reduction_duration": {
      "special_bonus_unique_visage_1": "+10",
      "value": "0"
    },
    "armor_reduction_per_hit": {
      "special_bonus_unique_visage_1": "+1",
      "value": "0"
    },
    "attack_range_buffer": "200",
    "back_distance": "75",
    "bonus_damage": {
      "CalculateSpellDamageTooltip": "0",
      "special_bonus_unique_visage_7": "+6",
      "value": "0"
    },
    "bonus_movement_speed": {
      "value": "0"
    },
    "familiar_armor": "2 3 4",
    "familiar_attack_damage": {
      "CalculateSpellDamageTooltip": "0",
      "value": "25 50 75"
    },
    "familiar_attack_range": {
      "special_bonus_facet_visage_faithful_followers": "+170",
      "value": "180"
    },
    "familiar_base_movespeed": {
      "special_bonus_facet_visage_faithful_followers": "+40",
      "value": "430"
    },
    "familiar_bounty": {
      "special_bonus_facet_visage_faithful_followers": "=50",
      "value": "100"
    },
    "familiar_count": {
      "special_bonus_unique_visage_6": "+1",
      "value": "2"
    },
    "familiar_hp": "500 600 700",
    "in_formation": {
      "special_bonus_facet_visage_faithful_followers": "+1",
      "value": "0"
    },
    "max_distance": {
      "affected_by_aoe_increase": "1",
      "value": "3500"
    },
    "recall_duration": "4",
    "return_distance": {
      "value": "1200"
    },
    "side_distance": "75"
  }
}
