{
  "Ability1": "kunkka_torrent",
  "Ability10": "special_bonus_unique_kunkka_tidebringer_slow",
  "Ability11": "special_bonus_unique_kunkka_3",
  "Ability12": "special_bonus_unique_kunkka_7",
  "Ability13": "special_bonus_unique_kunkka_2",
  "Ability14": "special_bonus_unique_kunkka_torrent_cooldown",
  "Ability15": "special_bonus_unique_kunkka_rum",
  "Ability16": "special_bonus_spell_aoe_100",
  "Ability17": "special_bonus_unique_kunkka_4",
  "Ability2": "kunkka_tidebringer",
  "Ability3": "kunkka_x_marks_the_spot",
  "Ability4": "kunkka_admirals_rum",
  "Ability5": "kunkka_tidal_wave",
  "Ability6": "kunkka_ghostship",
  "Ability7": "kunkka_return",
  "AbilityDraftAbilities": {
    "Ability1": "kunkka_torrent",
    "Ability2": "kunkka_tidebringer",
    "Ability3": "kunkka_x_marks_the_spot",
    "Ability4": "kunkka_ghostship"
  },
  "Adjectives": {
    "Aquatic": "1",
    "Bearded": "1",
    "Undead": "1"
  },
  "ArmorPhysical": "2",
  "AttackAcquisitionRange": "600",
  "AttackAnimationPoint": "0.400000",
  "AttackCapabilities": "DOTA_UNIT_CAP_MELEE_ATTACK",
  "AttackDamageMax": "36",
  "AttackDamageMin": "30",
  "AttackRange": "150",
  "AttackRate": "1.700000",
  "AttributeAgilityGain": "1.600000",
  "AttributeBaseAgility": "14",
  "AttributeBaseIntelligence": "18",
  "AttributeBaseStrength": "24",
  "AttributeIntelligenceGain": "1.800000",
  "AttributePrimary": "DOTA_ATTRIBUTE_STRENGTH",
  "AttributeStrengthGain": "3.600000",
  "BanSound": "kunkka_kunk_anger_04",
  "Bot": {
    "Build": {
      "1": "kunkka_tidebringer",
      "2": "kunkka_torrent",
      "3": "kunkka_tidebringer",
      "4": "kunkka_torrent",
      "5": "kunkka_tidebringer",
      "6": "kunkka_ghostship",
      "7": "kunkka_tidebringer",
      "8": "kunkka_torrent",
      "9": "kunkka_torrent",
      "10": "special_bonus_unique_kunkka_tidebringer_slow",
      "11": "kunkka_x_marks_the_spot",
      "12": "kunkka_ghostship",
      "13": "kunkka_x_marks_the_spot",
      "14": "kunkka_x_marks_the_spot",
      "15": "special_bonus_unique_kunkka_7",
      "16": "kunkka_x_marks_the_spot",
      "17": "",
      "18": "kunkka_ghostship",
      "19": "",
      "20": "special_bonus_unique_kunkka_torrent_cooldown",
      "21": "",
      "22": "",
      "23": "",
      "24": "",
      "25": "special_bonus_unique_kunkka_4"
    },
    "HeroType": "DOTA_BOT_TANK | DOTA_BOT_SEMI_CARRY | DOTA_BOT_PUSH_SUPPORT",
    "LaningInfo": {
      "ProvidesBabysit": "1",
      "ProvidesSetup": "1",
      "RequiresBabysit": "0",
      "RequiresFarm": "1",
      "RequiresSetup": "0",
      "SoloDesire": "0",
      "SurvivalRating": "2"
    },
    "Loadout": {
      "item_ancient_janggo": "ITEM_DERIVED | ITEM_SELLABLE",
      "item_belt_of_strength": "ITEM_EXTENSION",
      "item_black_king_bar": "ITEM_DERIVED",
      "item_blades_of_attack": [
        "ITEM_EXTENSION",
        "ITEM_EXTENSION"
      ],
      "item_boots": "ITEM_CORE",
      "item_branches": [
        "ITEM_CORE",
        "ITEM_CORE"
      ],
      "item_chainmail": "ITEM_EXTENSION",
      "item_clarity": "ITEM_CONSUMABLE | ITEM_SELLABLE",
      "item_claymore": "ITEM_EXTENSION",
      "item_demon_edge": "ITEM_EXTENSION",
      "item_flask": "ITEM_CONSUMABLE | ITEM_SELLABLE",
      "item_greater_crit": "ITEM_DERIVED",
      "item_lesser_crit": "ITEM_DERIVED",
      "item_magic_stick": "ITEM_CORE",
      "item_magic_wand": "ITEM_DERIVED | ITEM_SELLABLE",
      "item_mithril_hammer": "ITEM_EXTENSION",
      "item_ogre_axe": "ITEM_EXTENSION",
      "item_phase_boots": "ITEM_DERIVED",
      "item_recipe_ancient_janggo": "ITEM_EXTENSION",
      "item_recipe_black_king_bar": "ITEM_EXTENSION",
      "item_recipe_greater_crit": "ITEM_EXTENSION",
      "item_recipe_lesser_crit": "ITEM_EXTENSION",
      "item_recipe_magic_wand": "ITEM_CORE",
      "item_robe": "ITEM_EXTENSION",
      "item_tango": "ITEM_CONSUMABLE | ITEM_SELLABLE",
      "item_wind_lace": "ITEM_EXTENSION"
    }
  },
  "BotImplemented": "1",
  "BoundsHullName": "DOTA_HULL_SIZE_HERO",
  "CMEnabled": "1",
  "Complexity": "2",
  "Enabled": "1",
  "Facets": {
    "kunkka_grog": {
      "Color": "Yellow",
      "GradientID": "2",
      "Icon": "armor"
    },
    "kunkka_high_tide": {
      "Color": "Blue",
      "GradientID": "2",
      "Icon": "cooldown"
    }
  },
  "GameSoundsFile": "soundevents/game_sounds_heroes/game_sounds_kunkka.vsndevts",
  "GibType": "default",
  "HeroGlowColor": "50 150 165",
  "HeroID": "23",
  "HeroOrderID": "49",
  "HeroSelectSoundEffect": "Hero_Kunkka.Pick",
  "HeroUnlockOrder": "3",
  "IdleExpression": "scenes/kunkka/kunkka_exp_idle_01.vcd",
  "ItemSlots": {
    "0": {
      "MaxPolygonsLOD0": "2500",
      "MaxPolygonsLOD1": "1000",
      "SlotIndex": "0",
      "SlotName": "weapon",
      "SlotText": "#LoadoutSlot_Weapon",
      "TextureHeight": "256",
      "TextureWidth": "256"
    },
    "1": {
      "MaxPolygonsLOD0": "3000",
      "MaxPolygonsLOD1": "1200",
      "SlotIndex": "1",
      "SlotName": "head",
      "SlotText": "#LoadoutSlot_Head_Accessory",
      "TextureHeight": "256",
      "TextureWidth": "256"
    },
    "2": {
      "MaxPolygonsLOD0": "1500",
      "MaxPolygonsLOD1": "600",
      "SlotIndex": "2",
      "SlotName": "legs",
      "SlotText": "#LoadoutSlot_Legs",
      "TextureHeight": "256",
      "TextureWidth": "256"
    },
    "3": {
      "MaxPolygonsLOD0": "1500",
      "MaxPolygonsLOD1": "600",
      "SlotIndex": "3",
      "SlotName": "gloves",
      "SlotText": "#LoadoutSlot_Gloves",
      "TextureHeight": "128",
      "TextureWidth": "256"
    },
    "4": {
      "MaxPolygonsLOD0": "2500",
      "MaxPolygonsLOD1": "1000",
      "SlotIndex": "4",
      "SlotName": "back",
      "SlotText": "#LoadoutSlot_Back",
      "TextureHeight": "256",
      "TextureWidth": "256"
    },
    "5": {
      "MaxPolygonsLOD0": "2500",
      "MaxPolygonsLOD1": "1000",
      "SlotIndex": "5",
      "SlotName": "shoulder",
      "SlotText": "#LoadoutSlot_shoulder",
      "TextureHeight": "512",
      "TextureWidth": "512"
    },
    "6": {
      "MaxPolygonsLOD0": "1000",
      "MaxPolygonsLOD1": "400",
      "SlotIndex": "6",
      "SlotName": "neck",
      "SlotText": "#LoadoutSlot_Misc",
      "TextureHeight": "128",
      "TextureWidth": "256"
    },
    "7": {
      "MaxPolygonsLOD0": "1500",
      "MaxPolygonsLOD1": "600",
      "SlotIndex": "7",
      "SlotName": "belt",
      "SlotText": "#LoadoutSlot_Belt",
      "TextureHeight": "256",
      "TextureWidth": "256"
    },
    "8": {
      "SlotIndex": "8",
      "SlotName": "taunt",
      "SlotText": "#LoadoutSlot_Taunt"
    },
    "9": {
      "DisplayInLoadout": "0",
      "SlotIndex": "9",
      "SlotName": "ability_effects_1",
      "SlotText": "kunkka_torrent"
    },
    "10": {
      "DisplayInLoadout": "0",
      "SlotIndex": "10",
      "SlotName": "ability_effects_4",
      "SlotText": "kunkka_ghostship"
    },
    "11": {
      "DisplayInLoadout": "0",
      "SlotIndex": "11",
      "SlotName": "ability_effects_2",
      "SlotText": "kunkka_tidebringer"
    },
    "12": {
      "DisplayInLoadout": "0",
      "SlotIndex": "12",
      "SlotName": "ability_effects_3",
      "SlotText": "kunkka_x_marks_the_spot"
    },
    "13": {
      "SlotIndex": "13",
      "SlotName": "hero_effigy",
      "SlotText": "#LoadoutSlot_HeroEffigy"
    }
  },
  "LastHitChallengeRival": "npc_dota_hero_tidehunter",
  "LoadoutScale": "0.840000",
  "Model": "models/heroes/kunkka/kunkka.vmdl",
  "ModelScale": "0.840000",
  "MovementSpeed": "315",
  "NameAliases": "Admiral",
  "PickSound": "kunkka_kunk_spawn_11",
  "RenderablePortrait": {
    "Particles": {
      "particles/units/heroes/hero_kunkka/kunkka_loadout.vpcf": "loadout"
    }
  },
  "Role": "Carry,Support,Disabler,Initiator,Durable,Nuker",
  "Rolelevels": "2,1,2,2,1,1",
  "SimilarHeroes": "19,129,18",
  "SoundSet": "Hero_Kunkka",
  "SpectatorLoadoutScale": "0.94",
  "StatusHealthRegen": "0.75",
  "Team": "Good",
  "VersusScale": "0.840000",
  "VoiceFile": "soundevents/voscripts/game_sounds_vo_kunkka.vsndevts",
  "new_player_enable": "1",
  "particle_folder": "particles/units/heroes/hero_kunkka",
  "party_hat_effects": {
    "party_hat_effect_0": "particles/econ/events/frostivus_2024/frostivus_2024_hat_ambient_npc_dota_hero_kunkka.vpcf"
  },
  "precache": {
    "particle": "particles/econ/events/frostivus_2024/frostivus_2024_hat_ambient_npc_dota_hero_kunkka.vpcf"
  },
  "showcase_attachments": {
    "attach_hand2": "3",
    "attach_head": "4",
    "attach_sword": "2"
  },
  "workshop_guide_name": "Kunkka"
}
